a_cv2_putTrueTypeText/README.MD
a_cv2_putTrueTypeText/__init__.py
a_cv2_putTrueTypeText/requirements.txt
a_cv2_putTrueTypeText/thirdparty.json
a_cv2_putTrueTypeText-0.10.dist-info/LICENSE.rst
a_cv2_putTrueTypeText-0.10.dist-info/METADATA
a_cv2_putTrueTypeText-0.10.dist-info/WHEEL
a_cv2_putTrueTypeText-0.10.dist-info/top_level.txt
a_cv2_putTrueTypeText-0.10.dist-info/RECORD
