Metadata-Version: 2.1
Name: a-cv2-putTrueTypeText
Version: 0.10
Summary: Like cv2.putText, but with TrueType Fonts (ttf)
Home-page: https://github.com/hansalemaos/a_cv2_putTrueTypeText
Author: Johannes Fischer
Author-email: <aulasparticularesdealemaosp@gmail.com>
License: MIT
Keywords: opencv,cv2,TrueType,cv,TrueType Font,ttf,.ttf
Classifier: Development Status :: 4 - Beta
Classifier: Programming Language :: Python :: 3 :: Only
Classifier: Programming Language :: Python :: 3.9
Classifier: Topic :: Scientific/Engineering :: Visualization
Classifier: Topic :: Software Development :: Libraries :: Python Modules
Classifier: Topic :: Text Editors :: Text Processing
Classifier: Topic :: Text Processing :: General
Classifier: Topic :: Text Processing :: Indexing
Classifier: Topic :: Text Processing :: Filters
Classifier: Topic :: Utilities
License-File: LICENSE.rst
Requires-Dist: a-cv-imwrite-imread-plus
Requires-Dist: freetype-py
Requires-Dist: numpy
Requires-Dist: opencv-python
